{
    "0": {
        "OldPrice": 0,
        "Price": 23990,
        "ItemId": 603660,
        "Vendor": "Leran",
        "Description": "Тип: узкая; Тип установки: встраиваемая полностью; Вместимость: 10 комплектов; Расход воды: 9 л",
        "TypePrefix": "Встраиваемая посудомоечная машина",
        "Model": "Bdw 45-104",
        "Url": "https://rbt.ru/cat/vstraivaemaya_tehnika/vstraivaemye_posudomoechnye_mashiny/leran_bdw_45-104",
        "Name": "Встраиваемая посудомоечная машина Leran Bdw 45-104",
        "CategoryIds": 96,
        "comments": "31"
    },
    "1": {
        "OldPrice": 0,
        "Price": 30990,
        "ItemId": 446594,
        "Vendor": "Leran",
        "Description": "Тип: полноразмерная; Тип установки: встраиваемая полностью; Вместимость: 14 комплектов; Расход воды: 10 л",
        "TypePrefix": "Встраиваемая посудомоечная машина",
        "Model": "Bdw 60-148",
        "Url": "https://rbt.ru/cat/vstraivaemaya_tehnika/vstraivaemye_posudomoechnye_mashiny/leran_bdw_60-148",
        "Name": "Встраиваемая посудомоечная машина Leran Bdw 60-148",
        "CategoryIds": 96,
        "comments": "16"
    },
    "2": {
        "OldPrice": 0,
        "Price": 28990,
        "ItemId": 124567,
        "Vendor": "Leran",
        "Description": "Тип: полноразмерная; Тип установки: встраиваемая полностью; Вместимость: 14 комплектов; Расход воды: 11 л",
        "TypePrefix": "Встраиваемая посудомоечная машина",
        "Model": "Bdw 60-146",
        "Url": "https://rbt.ru/cat/vstraivaemaya_tehnika/vstraivaemye_posudomoechnye_mashiny/leran_bdw_60-146",
        "Name": "Встраиваемая посудомоечная машина Leran Bdw 60-146",
        "CategoryIds": 96,
        "comments": "15"
    },
    "3": {
        "OldPrice": 0,
        "Price": 28990,
        "ItemId": 372475,
        "Vendor": "Leran",
        "Description": "Тип: узкая; Тип установки: встраиваемая полностью; Вместимость: 10 комплектов; Расход воды: 8 л",
        "TypePrefix": "Встраиваемая посудомоечная машина",
        "Model": "Bdw 45-108",
        "Url": "https://rbt.ru/cat/vstraivaemaya_tehnika/vstraivaemye_posudomoechnye_mashiny/leran_bdw_45-108",
        "Name": "Встраиваемая посудомоечная машина Leran Bdw 45-108",
        "CategoryIds": 96,
        "comments": "34"
    },
    "4": {
        "OldPrice": 0,
        "Price": 26990,
        "ItemId": 124566,
        "Vendor": "Leran",
        "Description": "Тип: узкая; Тип установки: встраиваемая полностью; Вместимость: 10 комплектов; Расход воды: 9 л",
        "TypePrefix": "Встраиваемая посудомоечная машина",
        "Model": "Bdw 45-106",
        "Url": "https://rbt.ru/cat/vstraivaemaya_tehnika/vstraivaemye_posudomoechnye_mashiny/leran_bdw_45-106",
        "Name": "Встраиваемая посудомоечная машина Leran Bdw 45-106",
        "CategoryIds": 96,
        "comments": "27"
    },
    "5": {
        "OldPrice": 58999,
        "Price": 34999,
        "ItemId": 793065,
        "Vendor": "Beko",
        "Description": "Тип: узкая; Тип установки: встраиваемая полностью; Вместимость: 11 комплектов; Расход воды: 8.7 л",
        "TypePrefix": "Встраиваемая посудомоечная машина",
        "Model": "Bdis38122q",
        "Url": "https://rbt.ru/cat/vstraivaemaya_tehnika/vstraivaemye_posudomoechnye_mashiny/beko_bdis38122q",
        "Name": "Встраиваемая посудомоечная машина Beko Bdis38122q",
        "CategoryIds": 96,
        "comments": ""
    },
    "6": {
        "OldPrice": 0,
        "Price": 44999,
        "ItemId": 791319,
        "Vendor": "Beko",
        "Description": "Тип: узкая; Тип установки: встраиваемая полностью; Вместимость: 10 комплектов; Расход воды: 11.9 л",
        "TypePrefix": "Встраиваемая посудомоечная машина",
        "Model": "Bdis15020",
        "Url": "https://rbt.ru/cat/vstraivaemaya_tehnika/vstraivaemye_posudomoechnye_mashiny/beko_bdis15020",
        "Name": "Встраиваемая посудомоечная машина Beko Bdis15020",
        "CategoryIds": 96,
        "comments": ""
    },
    "7": {
        "OldPrice": 39999,
        "Price": 36999,
        "ItemId": 760372,
        "Vendor": "Gorenje",
        "Description": "Тип: полноразмерная; Тип установки: встраиваемая полностью; Вместимость: 14 комплектов; Расход воды: 11 л",
        "TypePrefix": "Встраиваемая посудомоечная машина",
        "Model": "Gv620e10",
        "Url": "https://rbt.ru/cat/vstraivaemaya_tehnika/vstraivaemye_posudomoechnye_mashiny/gorenje_gv620e10",
        "Name": "Встраиваемая посудомоечная машина Gorenje Gv620e10",
        "CategoryIds": 96,
        "comments": "15"
    },
    "8": {
        "OldPrice": 63999,
        "Price": 55999,
        "ItemId": 731787,
        "Vendor": "Haier",
        "Description": "Тип: полноразмерная; Тип установки: встраиваемая полностью; Вместимость: 14 комплектов; Расход воды: 0 л",
        "TypePrefix": "Встраиваемая посудомоечная машина",
        "Model": "Hdwe14-094ru",
        "Url": "https://rbt.ru/cat/vstraivaemaya_tehnika/vstraivaemye_posudomoechnye_mashiny/haier_hdwe14_094ru",
        "Name": "Встраиваемая посудомоечная машина Haier Hdwe14-094ru",
        "CategoryIds": 96,
        "comments": "3"
    },
    "9": {
        "OldPrice": 33999,
        "Price": 30499,
        "ItemId": 789556,
        "Vendor": "Gorenje",
        "Description": "Тип: узкая; Тип установки: встраиваемая полностью; Вместимость: 9 комплектов; Расход воды: 10 л",
        "TypePrefix": "Встраиваемая посудомоечная машина",
        "Model": "Gv52041",
        "Url": "https://rbt.ru/cat/vstraivaemaya_tehnika/vstraivaemye_posudomoechnye_mashiny/gorenje_gv52041",
        "Name": "Встраиваемая посудомоечная машина Gorenje Gv52041",
        "CategoryIds": 96,
        "comments": "1"
    },
    "10": {
        "OldPrice": 39999,
        "Price": 35999,
        "ItemId": 771951,
        "Vendor": "Gorenje",
        "Description": "Тип: узкая; Тип установки: встраиваемая полностью; Вместимость: 9 комплектов; Расход воды: 9 л",
        "TypePrefix": "Встраиваемая посудомоечная машина",
        "Model": "Gv541d10",
        "Url": "https://rbt.ru/cat/vstraivaemaya_tehnika/vstraivaemye_posudomoechnye_mashiny/gorenje_gv541d10",
        "Name": "Встраиваемая посудомоечная машина Gorenje Gv541d10",
        "CategoryIds": 96,
        "comments": "13"
    },
    "11": {
        "OldPrice": 0,
        "Price": 32999,
        "ItemId": 786744,
        "Vendor": "Midea",
        "Description": "Тип: узкая; Тип установки: встраиваемая полностью; Вместимость: 10 комплектов; Расход воды: 10 л",
        "TypePrefix": "Встраиваемая посудомоечная машина",
        "Model": "Mid45s130i",
        "Url": "https://rbt.ru/cat/vstraivaemaya_tehnika/vstraivaemye_posudomoechnye_mashiny/midea_mid45s130i",
        "Name": "Встраиваемая посудомоечная машина Midea Mid45s130i",
        "CategoryIds": 96,
        "comments": ""
    },
    "12": {
        "OldPrice": 0,
        "Price": 38999,
        "ItemId": 780809,
        "Vendor": "Haier",
        "Description": "Тип: узкая; Тип установки: встраиваемая полностью; Вместимость: 9 комплектов; Расход воды: 9 л",
        "TypePrefix": "Встраиваемая посудомоечная машина",
        "Model": "Hdwe9-191ru",
        "Url": "https://rbt.ru/cat/vstraivaemaya_tehnika/vstraivaemye_posudomoechnye_mashiny/haier_hdwe9_191ru",
        "Name": "Встраиваемая посудомоечная машина Haier Hdwe9-191ru",
        "CategoryIds": 96,
        "comments": ""
    },
    "13": {
        "OldPrice": 39999,
        "Price": 35999,
        "ItemId": 760371,
        "Vendor": "Gorenje",
        "Description": "Тип: полноразмерная; Тип установки: встраиваемая полностью; Вместимость: 13 комплектов; Расход воды: 11 л",
        "TypePrefix": "Встраиваемая посудомоечная машина",
        "Model": "Gv61212",
        "Url": "https://rbt.ru/cat/vstraivaemaya_tehnika/vstraivaemye_posudomoechnye_mashiny/gorenje_gv61212",
        "Name": "Встраиваемая посудомоечная машина Gorenje Gv61212",
        "CategoryIds": 96,
        "comments": "26"
    },
    "14": {
        "OldPrice": 0,
        "Price": 47999,
        "ItemId": 790277,
        "Vendor": "Beko",
        "Description": "Тип: полноразмерная; Тип установки: встраиваемая полностью; Вместимость: 13 комплектов; Расход воды: 12.9 л",
        "TypePrefix": "Встраиваемая посудомоечная машина",
        "Model": "Bdin14320",
        "Url": "https://rbt.ru/cat/vstraivaemaya_tehnika/vstraivaemye_posudomoechnye_mashiny/beko_bdin14320_i790277",
        "Name": "Встраиваемая посудомоечная машина Beko Bdin14320",
        "CategoryIds": 96,
        "comments": ""
    },
    "15": {
        "OldPrice": 45999,
        "Price": 41999,
        "ItemId": 666510,
        "Vendor": "Haier",
        "Description": "Тип: узкая; Тип установки: встраиваемая полностью; Вместимость: 10 комплектов; Расход воды: 10 л",
        "TypePrefix": "Встраиваемая посудомоечная машина",
        "Model": "Dw10-198bt3ru",
        "Url": "https://rbt.ru/cat/vstraivaemaya_tehnika/vstraivaemye_posudomoechnye_mashiny/haier_dw10-198bt3ru",
        "Name": "Встраиваемая посудомоечная машина Haier Dw10-198bt3ru",
        "CategoryIds": 96,
        "comments": "2"
    },
    "16": {
        "OldPrice": 43999,
        "Price": 39999,
        "ItemId": 666509,
        "Vendor": "Haier",
        "Description": "Тип: узкая; Тип установки: встраиваемая полностью; Вместимость: 10 комплектов; Расход воды: 10 л",
        "TypePrefix": "Встраиваемая посудомоечная машина",
        "Model": "Dw10-198bt2ru",
        "Url": "https://rbt.ru/cat/vstraivaemaya_tehnika/vstraivaemye_posudomoechnye_mashiny/haier_dw10-198bt2ru",
        "Name": "Встраиваемая посудомоечная машина Haier Dw10-198bt2ru",
        "CategoryIds": 96,
        "comments": "12"
    },
    "17": {
        "OldPrice": 0,
        "Price": 38999,
        "ItemId": 694871,
        "Vendor": "Krona",
        "Description": "Тип: узкая; Тип установки: встраиваемая полностью; Вместимость: 10 комплектов; Расход воды: 9 л",
        "TypePrefix": "Встраиваемая посудомоечная машина",
        "Model": "Kaskata 45 Bi",
        "Url": "https://rbt.ru/cat/vstraivaemaya_tehnika/vstraivaemye_posudomoechnye_mashiny/krona_kaskata_45_bi",
        "Name": "Встраиваемая посудомоечная машина Krona Kaskata 45 Bi",
        "CategoryIds": 96,
        "comments": "18"
    },
    "18": {
        "OldPrice": 71999,
        "Price": 52690,
        "ItemId": 791323,
        "Vendor": "Beko",
        "Description": "Тип: полноразмерная; Тип установки: встраиваемая полностью; Вместимость: 15 комплектов; Расход воды: 9.5 л",
        "TypePrefix": "Встраиваемая посудомоечная машина",
        "Model": "Bdin16520q",
        "Url": "https://rbt.ru/cat/vstraivaemaya_tehnika/vstraivaemye_posudomoechnye_mashiny/beko_bdin16520q",
        "Name": "Встраиваемая посудомоечная машина Beko Bdin16520q",
        "CategoryIds": 96,
        "comments": ""
    },
    "19": {
        "OldPrice": 0,
        "Price": 34990,
        "ItemId": 786743,
        "Vendor": "Midea",
        "Description": "Тип: полноразмерная; Тип установки: встраиваемая полностью; Вместимость: 14 комплектов; Расход воды: 10 л",
        "TypePrefix": "Встраиваемая посудомоечная машина",
        "Model": "Mid60s130i",
        "Url": "https://rbt.ru/cat/vstraivaemaya_tehnika/vstraivaemye_posudomoechnye_mashiny/midea_mid60s130i",
        "Name": "Встраиваемая посудомоечная машина Midea Mid60s130i",
        "CategoryIds": 96,
        "comments": ""
    },
    "20": {
        "OldPrice": 42999,
        "Price": 37499,
        "ItemId": 770811,
        "Vendor": "Gorenje",
        "Description": "Тип: узкая; Тип установки: встраиваемая полностью; Вместимость: 11 комплектов; Расход воды: 9 л",
        "TypePrefix": "Встраиваемая посудомоечная машина",
        "Model": "Gv561d10",
        "Url": "https://rbt.ru/cat/vstraivaemaya_tehnika/vstraivaemye_posudomoechnye_mashiny/gorenje_gv561d10",
        "Name": "Встраиваемая посудомоечная машина Gorenje Gv561d10",
        "CategoryIds": 96,
        "comments": "27"
    },
    "21": {
        "OldPrice": 44999,
        "Price": 32990,
        "ItemId": 702948,
        "Vendor": "Beko",
        "Description": "Тип: полноразмерная; Тип установки: встраиваемая полностью; Вместимость: 13 комплектов; Расход воды: 11.5 л",
        "TypePrefix": "Встраиваемая посудомоечная машина",
        "Model": "Din 14w13",
        "Url": "https://rbt.ru/cat/vstraivaemaya_tehnika/vstraivaemye_posudomoechnye_mashiny/beko_din_14w13",
        "Name": "Встраиваемая посудомоечная машина Beko Din 14w13",
        "CategoryIds": 96,
        "comments": "119"
    },
    "22": {
        "OldPrice": 0,
        "Price": 37999,
        "ItemId": 744222,
        "Vendor": "Electrolux",
        "Description": "Тип: узкая; Тип установки: встраиваемая полностью; Вместимость: 9 комплектов; Расход воды: 9.9 л",
        "TypePrefix": "Встраиваемая посудомоечная машина",
        "Model": "Eea912100l",
        "Url": "https://rbt.ru/cat/vstraivaemaya_tehnika/vstraivaemye_posudomoechnye_mashiny/electrolux_eea912100l",
        "Name": "Встраиваемая посудомоечная машина Electrolux Eea912100l",
        "CategoryIds": 96,
        "comments": "58"
    },
    "23": {
        "OldPrice": 39999,
        "Price": 32999,
        "ItemId": 745591,
        "Vendor": "Gorenje",
        "Description": "Тип: полноразмерная; Тип установки: встраиваемая полностью; Вместимость: 13 комплектов; Расход воды: 11 л",
        "TypePrefix": "Встраиваемая посудомоечная машина",
        "Model": "Gv62040",
        "Url": "https://rbt.ru/cat/vstraivaemaya_tehnika/vstraivaemye_posudomoechnye_mashiny/gorenje_gv62040",
        "Name": "Встраиваемая посудомоечная машина Gorenje Gv62040",
        "CategoryIds": 96,
        "comments": ""
    },
    "24": {
        "OldPrice": 0,
        "Price": 50999,
        "ItemId": 746923,
        "Vendor": "Haier",
        "Description": "Тип: узкая; Тип установки: встраиваемая полностью; Вместимость: 11 комплектов; Расход воды: 7.6 л",
        "TypePrefix": "Встраиваемая посудомоечная машина",
        "Model": "Hdwe11-194ru",
        "Url": "https://rbt.ru/cat/vstraivaemaya_tehnika/vstraivaemye_posudomoechnye_mashiny/haier_hdwe11_194ru",
        "Name": "Встраиваемая посудомоечная машина Haier Hdwe11-194ru",
        "CategoryIds": 96,
        "comments": "2"
    },
    "25": {
        "OldPrice": 48999,
        "Price": 30999,
        "ItemId": 759858,
        "Vendor": "Beko",
        "Description": "Тип: узкая; Тип установки: встраиваемая полностью; Вместимость: 10 комплектов; Расход воды: 9.5 л",
        "TypePrefix": "Встраиваемая посудомоечная машина",
        "Model": "Dis26022",
        "Url": "https://rbt.ru/cat/vstraivaemaya_tehnika/vstraivaemye_posudomoechnye_mashiny/beko_dis26022",
        "Name": "Встраиваемая посудомоечная машина Beko Dis26022",
        "CategoryIds": 96,
        "comments": "55"
    },
    "26": {
        "OldPrice": 0,
        "Price": 39999,
        "ItemId": 772307,
        "Vendor": "Hansa",
        "Description": "Тип: полноразмерная; Тип установки: встраиваемая полностью; Вместимость: 10 комплектов; Расход воды: 9 л",
        "TypePrefix": "Встраиваемая посудомоечная машина",
        "Model": "Zim 426 Tq",
        "Url": "https://rbt.ru/cat/vstraivaemaya_tehnika/vstraivaemye_posudomoechnye_mashiny/hansa_zim_426_tq",
        "Name": "Встраиваемая посудомоечная машина Hansa Zim 426 Tq",
        "CategoryIds": 96,
        "comments": ""
    },
    "27": {
        "OldPrice": 0,
        "Price": 52999,
        "ItemId": 780808,
        "Vendor": "Haier",
        "Description": "Тип: полноразмерная; Тип установки: встраиваемая полностью; Вместимость: 13 комплектов; Расход воды: 11 л",
        "TypePrefix": "Встраиваемая посудомоечная машина",
        "Model": "Hdwe13-191ru",
        "Url": "https://rbt.ru/cat/vstraivaemaya_tehnika/vstraivaemye_posudomoechnye_mashiny/haier_hdwe13_191ru",
        "Name": "Встраиваемая посудомоечная машина Haier Hdwe13-191ru",
        "CategoryIds": 96,
        "comments": ""
    },
    "28": {
        "OldPrice": 0,
        "Price": 33999,
        "ItemId": 784777,
        "Vendor": "Hansa",
        "Description": "Тип: полноразмерная; Тип установки: встраиваемая полностью; Вместимость: 13 комплектов; Расход воды: 11 л",
        "TypePrefix": "Встраиваемая посудомоечная машина",
        "Model": "Hansa Zim647tq",
        "Url": "https://rbt.ru/cat/vstraivaemaya_tehnika/vstraivaemye_posudomoechnye_mashiny/hansa_zim647tq",
        "Name": "Встраиваемая посудомоечная машина Hansa Hansa Zim647tq",
        "CategoryIds": 96,
        "comments": ""
    },
    "29": {
        "OldPrice": 0,
        "Price": 42999,
        "ItemId": 790775,
        "Vendor": "Midea",
        "Description": "Тип: узкая; Тип установки: встраиваемая полностью; Вместимость: 11 комплектов; Расход воды: 9 л",
        "TypePrefix": "Встраиваемая посудомоечная машина",
        "Model": "Mid45s430i",
        "Url": "https://rbt.ru/cat/vstraivaemaya_tehnika/vstraivaemye_posudomoechnye_mashiny/midea_mid45s430i",
        "Name": "Встраиваемая посудомоечная машина Midea Mid45s430i",
        "CategoryIds": 96,
        "comments": ""
    },
    "30": {
        "OldPrice": 0,
        "Price": 44999,
        "ItemId": 790776,
        "Vendor": "Midea",
        "Description": "Тип: полноразмерная; Тип установки: встраиваемая полностью; Вместимость: 14 комплектов; Расход воды: 11 л",
        "TypePrefix": "Встраиваемая посудомоечная машина",
        "Model": "Mid60s430i",
        "Url": "https://rbt.ru/cat/vstraivaemaya_tehnika/vstraivaemye_posudomoechnye_mashiny/midea_mid60s430i",
        "Name": "Встраиваемая посудомоечная машина Midea Mid60s430i",
        "CategoryIds": 96,
        "comments": ""
    },
    "31": {
        "OldPrice": 0,
        "Price": 51999,
        "ItemId": 791320,
        "Vendor": "Beko",
        "Description": "Тип: узкая; Тип установки: встраиваемая полностью; Вместимость: 10 комплектов; Расход воды: 9.5 л",
        "TypePrefix": "Встраиваемая посудомоечная машина",
        "Model": "Bdis16020",
        "Url": "https://rbt.ru/cat/vstraivaemaya_tehnika/vstraivaemye_posudomoechnye_mashiny/beko_bdis16020",
        "Name": "Встраиваемая посудомоечная машина Beko Bdis16020",
        "CategoryIds": 96,
        "comments": ""
    },
    "32": {
        "OldPrice": 0,
        "Price": 32999,
        "ItemId": 792694,
        "Vendor": "Krona",
        "Description": "Тип: полноразмерная; Тип установки: встраиваемая полностью; Вместимость: 12 комплектов; Расход воды: 11 л",
        "TypePrefix": "Встраиваемая посудомоечная машина",
        "Model": "Rossa 60 Bi",
        "Url": "https://rbt.ru/cat/vstraivaemaya_tehnika/vstraivaemye_posudomoechnye_mashiny/krona_rossa_60_bi",
        "Name": "Встраиваемая посудомоечная машина Krona Rossa 60 Bi",
        "CategoryIds": 96,
        "comments": ""
    },
    "33": {
        "OldPrice": 0,
        "Price": 38999,
        "ItemId": 792715,
        "Vendor": "Hansa",
        "Description": "Тип: узкая; Тип установки: встраиваемая полностью; Вместимость: 10 комплектов; Расход воды: 9 л",
        "TypePrefix": "Встраиваемая посудомоечная машина",
        "Model": "Zim435eq",
        "Url": "https://rbt.ru/cat/vstraivaemaya_tehnika/vstraivaemye_posudomoechnye_mashiny/hansa_zim435eq",
        "Name": "Встраиваемая посудомоечная машина Hansa Zim435eq",
        "CategoryIds": 96,
        "comments": ""
    }
}