{
    "0": {
        "OldPrice": 0,
        "Price": 2890,
        "ItemId": 429472,
        "Vendor": "Huter",
        "Description": "Тип: переносной; Мощность: 600 Вт; Травосборник: нет; Мульчирование: нет",
        "TypePrefix": "Триммер",
        "Model": "Get-600",
        "Url": "https://rbt.ru/cat/sadovaya_tehnika/trimmery/huter_get-600",
        "Name": "Триммер Huter Get-600",
        "CategoryIds": 56,
        "comments": "219"
    },
    "1": {
        "OldPrice": 1890,
        "Price": 1440,
        "ItemId": 754351,
        "Vendor": "Ресанта",
        "Description": "Тип: переносной; Мощность: 400 Вт; Травосборник: нет; Мульчирование: нет",
        "TypePrefix": "Триммер",
        "Model": "Эт-450",
        "Url": "https://rbt.ru/cat/sadovaya_tehnika/trimmery/resanta_et_450",
        "Name": "Триммер Ресанта Эт-450",
        "CategoryIds": 56,
        "comments": "20"
    },
    "2": {
        "OldPrice": 9590,
        "Price": 7399,
        "ItemId": 455927,
        "Vendor": "Ставр",
        "Description": "Тип: переносной; Мощность: 1700 Вт; Травосборник: нет; Мульчирование: нет",
        "TypePrefix": "Триммер",
        "Model": "Тэ-1700р",
        "Url": "https://rbt.ru/cat/sadovaya_tehnika/trimmery/stavr_te-1700r",
        "Name": "Триммер Ставр Тэ-1700р",
        "CategoryIds": 56,
        "comments": "189"
    },
    "3": {
        "OldPrice": 3990,
        "Price": 2890,
        "ItemId": 696811,
        "Vendor": "Kolner",
        "Description": "Тип: переносной; Мощность: 600 Вт; Травосборник: нет; Мульчирование: нет",
        "TypePrefix": "Триммер",
        "Model": "Ket 600",
        "Url": "https://rbt.ru/cat/sadovaya_tehnika/trimmery/kolner_ket_600",
        "Name": "Триммер Kolner Ket 600",
        "CategoryIds": 56,
        "comments": "69"
    },
    "4": {
        "OldPrice": 0,
        "Price": 7190,
        "ItemId": 373775,
        "Vendor": "Huter",
        "Description": "Тип: переносной; Мощность: 2500 Вт; Травосборник: нет; Мульчирование: нет",
        "TypePrefix": "Триммер",
        "Model": "Ggt-2500s",
        "Url": "https://rbt.ru/cat/sadovaya_tehnika/trimmery/huter_ggt-2500s",
        "Name": "Триммер Huter Ggt-2500s",
        "CategoryIds": 56,
        "comments": "130"
    },
    "5": {
        "OldPrice": 0,
        "Price": 6690,
        "ItemId": 652195,
        "Vendor": "Huter",
        "Description": "Тип: переносной; Мощность: 1500 Вт; Травосборник: нет; Мульчирование: нет",
        "TypePrefix": "Триммер",
        "Model": "Ggt-1500sx",
        "Url": "https://rbt.ru/cat/sadovaya_tehnika/trimmery/huter_ggt-1500sx",
        "Name": "Триммер Huter Ggt-1500sx",
        "CategoryIds": 56,
        "comments": "47"
    },
    "6": {
        "OldPrice": 0,
        "Price": 6190,
        "ItemId": 373767,
        "Vendor": "Huter",
        "Description": "Тип: переносной; Мощность: 1000 Вт; Травосборник: нет; Мульчирование: нет",
        "TypePrefix": "Триммер",
        "Model": "Ggt-1000s",
        "Url": "https://rbt.ru/cat/sadovaya_tehnika/trimmery/huter_ggt-1000s",
        "Name": "Триммер Huter Ggt-1000s",
        "CategoryIds": 56,
        "comments": "85"
    },
    "7": {
        "OldPrice": 0,
        "Price": 3990,
        "ItemId": 373810,
        "Vendor": "Huter",
        "Description": "Тип: переносной; Мощность: 1000 Вт; Травосборник: нет; Мульчирование: нет",
        "TypePrefix": "Триммер",
        "Model": "Get-1000s",
        "Url": "https://rbt.ru/cat/sadovaya_tehnika/trimmery/huter_get-1000s",
        "Name": "Триммер Huter Get-1000s",
        "CategoryIds": 56,
        "comments": "198"
    }
}